main.py
onboard_dev-0.1.0.dist-info/METADATA
onboard_dev-0.1.0.dist-info/WHEEL
onboard_dev-0.1.0.dist-info/top_level.txt
onboard_dev-0.1.0.dist-info/RECORD
