Metadata-Version: 2.4
Name: onboard-dev
Version: 0.1.0
Summary: To onboard
Requires-Python: >=3.10
